Entratools/General.py
Entratools/__init__.py
Entratools/cli_commands.py
Entratools/template.py
Entratools-0.1.3.dist-info/METADATA
Entratools-0.1.3.dist-info/WHEEL
Entratools-0.1.3.dist-info/entry_points.txt
Entratools-0.1.3.dist-info/top_level.txt
Entratools-0.1.3.dist-info/RECORD
