Metadata-Version: 2.1
Name: Entratools
Version: 0.1.3
Summary: Tools for easier development
Home-page: UNKNOWN
Author: Emiliano Fripp
License: UNKNOWN
Platform: UNKNOWN
